validus_pkg_test/Fund_Model.py
validus_pkg_test/SV_MC.py
validus_pkg_test/__init__.py
validus_pkg_test/testing/__init__.py
validus_pkg_test/testing/import unittest.py
validus_pkg_test/testing/test_Fund.py
validus_pkg_test/testing/test_stoch.py
validus_pkg_test-0.0.2.dist-info/LICENSE.md
validus_pkg_test-0.0.2.dist-info/METADATA
validus_pkg_test-0.0.2.dist-info/WHEEL
validus_pkg_test-0.0.2.dist-info/top_level.txt
validus_pkg_test-0.0.2.dist-info/RECORD
