Metadata-Version: 2.1
Name: validus-pkg-test
Version: 0.0.2
Summary: Case Study Package
Home-page: https://github.com/pypa/sampleproject
Author: Stephen McGrath
Author-email: s_mcgrath1912@live.co.uk
License: UNKNOWN
Platform: UNKNOWN
Classifier: Programming Language :: Python :: 3
Classifier: License :: OSI Approved :: MIT License
Classifier: Operating System :: OS Independent
